voight_kampff/__init__.py
voight_kampff/__main__.py
voight_kampff/task.py
voight_kampff/version.py
voight_kampff-1.0.0.dist-info/LICENSE
voight_kampff-1.0.0.dist-info/METADATA
voight_kampff-1.0.0.dist-info/WHEEL
voight_kampff-1.0.0.dist-info/entry_points.txt
voight_kampff-1.0.0.dist-info/top_level.txt
voight_kampff-1.0.0.dist-info/RECORD
