Metadata-Version: 2.1
Name: voight-kampff
Version: 1.0.0
Summary: Simple command line app for running Python linters.
Home-page: https://github.com/sorenlind/voight-kampff/
Author: Soren Kristiansen
Author-email: soren@gutsandglory.dk
Classifier: Development Status :: 3 - Alpha
Classifier: Intended Audience :: Developers
Classifier: Intended Audience :: Science/Research
Classifier: License :: OSI Approved :: MIT License
Classifier: Operating System :: OS Independent
Classifier: Programming Language :: Python :: 3.8
License-File: LICENSE
Requires-Dist: black
Requires-Dist: flake8
Requires-Dist: isort
Requires-Dist: pyenchant
Requires-Dist: pylint
Provides-Extra: dev
Requires-Dist: coverage ; extra == 'dev'
Requires-Dist: flake8-annotations ; extra == 'dev'
Requires-Dist: flake8-bandit ; extra == 'dev'
Requires-Dist: flake8-docstrings ; extra == 'dev'
Requires-Dist: flake8-plus ; extra == 'dev'
Requires-Dist: flake8-pytest-style ; extra == 'dev'
Requires-Dist: pytest-cov ; extra == 'dev'
Requires-Dist: pytest-mock ; extra == 'dev'
Requires-Dist: pytest ; extra == 'dev'
Requires-Dist: rope ; extra == 'dev'
Requires-Dist: tox ; extra == 'dev'
Provides-Extra: test
Requires-Dist: coverage ; extra == 'test'
Requires-Dist: pytest-cov ; extra == 'test'
Requires-Dist: pytest-mock ; extra == 'test'
Requires-Dist: pytest ; extra == 'test'
Requires-Dist: tox ; extra == 'test'
